chrome_devtools_mcp_fork/__init__.py
chrome_devtools_mcp_fork/__main__.py
chrome_devtools_mcp_fork/client.py
chrome_devtools_mcp_fork/main.py
chrome_devtools_mcp_fork/tools/__init__.py
chrome_devtools_mcp_fork/tools/browser.py
chrome_devtools_mcp_fork/tools/console.py
chrome_devtools_mcp_fork/tools/css.py
chrome_devtools_mcp_fork/tools/dom.py
chrome_devtools_mcp_fork/tools/network.py
chrome_devtools_mcp_fork/tools/performance.py
chrome_devtools_mcp_fork/tools/storage.py
chrome_devtools_mcp_fork/tools/utils.py
chrome_devtools_mcp_fork/utils/__init__.py
chrome_devtools_mcp_fork/utils/helpers.py
chrome_devtools_mcp_fork-2.0.1.dist-info/METADATA
chrome_devtools_mcp_fork-2.0.1.dist-info/WHEEL
chrome_devtools_mcp_fork-2.0.1.dist-info/entry_points.txt
chrome_devtools_mcp_fork-2.0.1.dist-info/top_level.txt
chrome_devtools_mcp_fork-2.0.1.dist-info/RECORD
