Metadata-Version: 2.4
Name: chrome-devtools-mcp-fork
Version: 2.0.1
Summary: MCP server for Chrome DevTools integration - enable AI assistants to control browsers for web development debugging
Author: withLinda13
License: MIT
Project-URL: Homepage, https://github.com/withLinda/chrome-devtools-mcp-fork
Project-URL: Bug Reports, https://github.com/withLinda/chrome-devtools-mcp-fork/issues
Project-URL: Source, https://github.com/withLinda/chrome-devtools-mcp-fork
Classifier: Development Status :: 4 - Beta
Classifier: Intended Audience :: Developers
Classifier: License :: OSI Approved :: MIT License
Classifier: Programming Language :: Python :: 3
Classifier: Programming Language :: Python :: 3.10
Classifier: Programming Language :: Python :: 3.11
Classifier: Programming Language :: Python :: 3.12
Requires-Python: >=3.10
Requires-Dist: mcp>=1.0.0
Requires-Dist: websocket-client>=1.0.0
Requires-Dist: requests>=2.25.0
Provides-Extra: test
Requires-Dist: pytest>=8.0.0; extra == "test"
Requires-Dist: pytest-asyncio>=0.23.0; extra == "test"
Provides-Extra: dev
Requires-Dist: pytest>=8.0.0; extra == "dev"
Requires-Dist: pytest-asyncio>=0.23.0; extra == "dev"
Requires-Dist: ruff>=0.1.0; extra == "dev"
Requires-Dist: mypy>=1.0.0; extra == "dev"
Requires-Dist: types-requests>=2.25.0; extra == "dev"
